{
  "exercises": [
    {
      "id": "e1",
      "name": "Back Squats",
      "muscleGroup": "Legs"
    },
    {
      "id": "e2",
      "name": "Bench Press",
      "muscleGroup": "Chest"
    },
    {
      "id": "e3",
      "name": "Shoulder Press",
      "muscleGroup": "Shoulders"
    },
    {
      "id": "e4",
      "name": "Pull Up",
      "muscleGroup": "Back and Biceps"
    }
  ],
  "logs": [
    {
      "id": "l1",
      "exerciseId": "e2",
      "date": "2026-01-26",
      "weightKg": 70,
      "reps": 6
    },
    {
      "id": "l2",
      "exerciseId": "e1",
      "date": "2026-01-27",
      "weightKg": 100,
      "reps": 6
    }
  ]
}